click_aliasing/__init__.py
click_aliasing-1.0.0.dist-info/LICENSE
click_aliasing-1.0.0.dist-info/METADATA
click_aliasing-1.0.0.dist-info/WHEEL
click_aliasing-1.0.0.dist-info/RECORD
