Metadata-Version: 2.1
Name: click-aliasing
Version: 1.0.0
Summary: Enable aliasing and unique matching for Click
License: MIT
Author: tjzegmott
Author-email: tzegmott@gmail.com
Requires-Python: >=3.8,<4.0
Classifier: License :: OSI Approved :: MIT License
Classifier: Programming Language :: Python :: 3
Classifier: Programming Language :: Python :: 3.8
Classifier: Programming Language :: Python :: 3.9
Classifier: Programming Language :: Python :: 3.10
Classifier: Programming Language :: Python :: 3.11
Requires-Dist: click (>=8.1.3,<9.0.0)
